{
 "kills_total":{
  "0":20,
  "1":21,
  "2":11,
  "3":9,
  "4":12,
  "5":9,
  "6":22,
  "7":9,
  "8":19,
  "9":12
 },
 "deaths_total":{
  "0":15,
  "1":14,
  "2":14,
  "3":17,
  "4":15,
  "5":13,
  "6":17,
  "7":12,
  "8":13,
  "9":14
 },
 "headshot_kills_total":{
  "0":10,
  "1":15,
  "2":6,
  "3":5,
  "4":3,
  "5":4,
  "6":8,
  "7":5,
  "8":10,
  "9":8
 },
 "ace_rounds_total":{
  "0":0,
  "1":0,
  "2":0,
  "3":0,
  "4":0,
  "5":0,
  "6":0,
  "7":0,
  "8":0,
  "9":0
 },
 "4k_rounds_total":{
  "0":0,
  "1":1,
  "2":0,
  "3":0,
  "4":0,
  "5":0,
  "6":0,
  "7":0,
  "8":1,
  "9":0
 },
 "3k_rounds_total":{
  "0":2,
  "1":1,
  "2":0,
  "3":0,
  "4":1,
  "5":1,
  "6":2,
  "7":0,
  "8":0,
  "9":0
 },
 "mvps":{
  "0":6,
  "1":3,
  "2":1,
  "3":0,
  "4":2,
  "5":1,
  "6":3,
  "7":1,
  "8":5,
  "9":1
 },
 "tick":{
  "0":182581,
  "1":182581,
  "2":182581,
  "3":182581,
  "4":182581,
  "5":182581,
  "6":182581,
  "7":182581,
  "8":182581,
  "9":182581
 },
 "steamid":{
  "0":76561198178209109,
  "1":76561197980244859,
  "2":76561198104626893,
  "3":76561199137143905,
  "4":76561198017982577,
  "5":76561198202417343,
  "6":76561198276534844,
  "7":76561198001557762,
  "8":76561198410750263,
  "9":76561198110806694
 },
 "name":{
  "0":"xfl0ud 1XBET",
  "1":"twist",
  "2":"LNZ 1XBET",
  "3":"yxngstxr 1XBET",
  "4":"PlesseN",
  "5":"avid",
  "6":"b0denmaster",
  "7":"robiin",
  "8":"jottAAA 1XBET",
  "9":"SaMey 1XBET"
 }
}