{
 "kills_total":{
  "0":25,
  "1":10,
  "2":14,
  "3":11,
  "4":14,
  "5":0,
  "6":15,
  "7":8,
  "8":6,
  "9":15,
  "10":12
 },
 "deaths_total":{
  "0":15,
  "1":14,
  "2":11,
  "3":16,
  "4":14,
  "5":0,
  "6":9,
  "7":16,
  "8":11,
  "9":10,
  "10":15
 },
 "headshot_kills_total":{
  "0":5,
  "1":2,
  "2":5,
  "3":2,
  "4":6,
  "5":0,
  "6":8,
  "7":3,
  "8":3,
  "9":4,
  "10":3
 },
 "ace_rounds_total":{
  "0":0,
  "1":0,
  "2":0,
  "3":0,
  "4":0,
  "5":0,
  "6":0,
  "7":0,
  "8":0,
  "9":0,
  "10":0
 },
 "4k_rounds_total":{
  "0":1,
  "1":0,
  "2":0,
  "3":0,
  "4":0,
  "5":0,
  "6":0,
  "7":0,
  "8":0,
  "9":0,
  "10":1
 },
 "3k_rounds_total":{
  "0":3,
  "1":0,
  "2":1,
  "3":1,
  "4":2,
  "5":0,
  "6":0,
  "7":1,
  "8":0,
  "9":0,
  "10":0
 },
 "mvps":{
  "0":6,
  "1":0,
  "2":3,
  "3":1,
  "4":4,
  "5":0,
  "6":3,
  "7":1,
  "8":0,
  "9":1,
  "10":1
 },
 "tick":{
  "0":179179,
  "1":179179,
  "2":179179,
  "3":179179,
  "4":179179,
  "5":179179,
  "6":179179,
  "7":179179,
  "8":179179,
  "9":179179,
  "10":179179
 },
 "steamid":{
  "0":76561198001782167,
  "1":76561197975427598,
  "2":76561198297390513,
  "3":76561198115155673,
  "4":76561198845573161,
  "5":76561197987460547,
  "6":76561198109574863,
  "7":76561198079367889,
  "8":76561198057884377,
  "9":76561198154172820,
  "10":76561198123795664
 },
 "name":{
  "0":"Fawx",
  "1":"Shivanee",
  "2":"mira",
  "3":"Jundiya",
  "4":"JLee",
  "5":"Coach | cy",
  "6":"bezdaria",
  "7":"tbear",
  "8":"rbn",
  "9":"PiggyKiKi",
  "10":"CANNIBAL"
 }
}